real_fractions/__init__.py
real_fractions/convert.py
real_fractions/core.py
real_fractions/main.py
real_fractions/operation.py
real_fractions-1.1.1.dist-info/LICENSE
real_fractions-1.1.1.dist-info/METADATA
real_fractions-1.1.1.dist-info/WHEEL
real_fractions-1.1.1.dist-info/top_level.txt
real_fractions-1.1.1.dist-info/RECORD
