Metadata-Version: 2.1
Name: real-fractions
Version: 1.1.1
Summary: Add all types of functions with fractions
Home-page: https://github.com/LuckJMG/RealFractions
Author: Lucas Mosquera
Author-email: lucas.mosquera13@gmail.com
Maintainer: Lucas Mosquera
Maintainer-email: lucas.mosquera13@gmail.com
License: MIT License
Platform: UNKNOWN
Classifier: Programming Language :: Python :: 3
Classifier: License :: OSI Approved :: MIT License
Classifier: Operating System :: OS Independent
Requires-Python: >=3.6
